emoji_index/__init__.py
emoji_index/main.py
emoji_index/data/__init__.py
emoji_index/data/emoji_data.py
emoji_index/data/emojis.py
emoji_index/objects/emoji.py
emoji_index-0.1.2.dist-info/licenses/LICENSE
emoji_index-0.1.2.dist-info/licenses/LICENSE_UNICODE.txt
emoji_index-0.1.2.dist-info/METADATA
emoji_index-0.1.2.dist-info/WHEEL
emoji_index-0.1.2.dist-info/top_level.txt
emoji_index-0.1.2.dist-info/RECORD
