Metadata-Version: 2.4
Name: emoji-index
Version: 0.1.2
Summary: A lightweight extension to the emoji library providing indexed traversal of emoji characters for selection menus
Author-email: nQuest Corporation <support@nquest.io>
License-Expression: Apache-2.0
Project-URL: Homepage, https://github.com/nquest-corp/emoji-index
Project-URL: Repository, https://github.com/nquest-corp/emoji-index
Project-URL: Issues, https://github.com/nquest-corp/emoji-index/issues
Keywords: emoji,unicode,index,emoji-data,emoji-picker
Classifier: Development Status :: 4 - Beta
Classifier: Intended Audience :: Developers
Classifier: Programming Language :: Python :: 3
Classifier: Programming Language :: Python :: 3.10
Classifier: Programming Language :: Python :: 3.11
Classifier: Programming Language :: Python :: 3.12
Classifier: Programming Language :: Python :: 3.13
Classifier: Topic :: Software Development :: Libraries :: Python Modules
Classifier: Topic :: Text Processing
Requires-Python: >=3.10
License-File: LICENSE
License-File: LICENSE_UNICODE.txt
Requires-Dist: emoji>=2.9.0
Dynamic: license-file
